selflayer/__init__.py
selflayer/__main__.py
selflayer/ai.py
selflayer/cli.py
selflayer/config.py
selflayer/models.py
selflayer/search.py
selflayer/tui.py
selflayer/web.py
selflayer-0.2.1.dist-info/licenses/LICENSE
selflayer-0.2.1.dist-info/METADATA
selflayer-0.2.1.dist-info/WHEEL
selflayer-0.2.1.dist-info/entry_points.txt
selflayer-0.2.1.dist-info/top_level.txt
selflayer-0.2.1.dist-info/RECORD
