Metadata-Version: 2.4
Name: selflayer
Version: 0.2.1
Summary: SelfLayer - AI-powered terminal web browser for content analysis and research
Author-email: Anton Vice <anton@selflayer.com>
Maintainer-email: Anton Vice <anton@selflayer.com>
Project-URL: Homepage, https://github.com/antonvice/selflayer
Project-URL: Repository, https://github.com/antonvice/selflayer
Project-URL: Bug-Tracker, https://github.com/antonvice/selflayer/issues
Project-URL: Documentation, https://github.com/antonvice/selflayer#readme
Keywords: web,browser,ai,research,analysis,terminal,cli
Classifier: Development Status :: 4 - Beta
Classifier: Intended Audience :: Developers
Classifier: Intended Audience :: Science/Research
Classifier: License :: OSI Approved :: MIT License
Classifier: Operating System :: OS Independent
Classifier: Programming Language :: Python :: 3
Classifier: Programming Language :: Python :: 3.11
Classifier: Programming Language :: Python :: 3.12
Classifier: Topic :: Internet :: WWW/HTTP :: Browsers
Classifier: Topic :: Scientific/Engineering :: Artificial Intelligence
Classifier: Topic :: Text Processing :: Linguistic
Requires-Python: >=3.11
License-File: LICENSE
Requires-Dist: beautifulsoup4>=4.12.0
Requires-Dist: ddgs>=6.0.0
Requires-Dist: google-generativeai>=0.7.0
Requires-Dist: httpx>=0.25.0
Requires-Dist: pydantic>=2.5.0
Requires-Dist: pydantic-ai>=0.0.13
Requires-Dist: python-dotenv>=1.0.0
Requires-Dist: rich>=13.7.0
Provides-Extra: dev
Requires-Dist: black>=23.0.0; extra == "dev"
Requires-Dist: isort>=5.12.0; extra == "dev"
Requires-Dist: pytest>=7.4.0; extra == "dev"
Requires-Dist: pytest-asyncio>=0.21.0; extra == "dev"
Requires-Dist: pytest-cov>=4.1.0; extra == "dev"
Requires-Dist: pytest-mock>=3.11.0; extra == "dev"
Requires-Dist: pre-commit>=3.0.0; extra == "dev"
Requires-Dist: mypy>=1.6.0; extra == "dev"
Requires-Dist: ruff>=0.1.0; extra == "dev"
Provides-Extra: test
Requires-Dist: pytest>=7.4.0; extra == "test"
Requires-Dist: pytest-asyncio>=0.21.0; extra == "test"
Requires-Dist: pytest-cov>=4.1.0; extra == "test"
Requires-Dist: pytest-mock>=3.11.0; extra == "test"
Dynamic: license-file
